rsml_python/__init__.py
rsml_python-1.0.5.dist-info/METADATA
rsml_python-1.0.5.dist-info/WHEEL
rsml_python-1.0.5.dist-info/licenses/LICENSE
rsml_python-1.0.5.dist-info/RECORD
