Metadata-Version: 2.4
Name: rsml_python
Version: 1.0.5
Summary: RedSeaMarkupLanguage support for Python.
Project-URL: Homepage, https://github.com/OceanApocalypseStudios/RSML.Python
Project-URL: Bug Tracker, https://github.com/OceanApocalypseStudios/RSML.Python/issues
Author-email: MF366 <real_mf366@yahoo.com>
License-File: LICENSE
Classifier: License :: OSI Approved :: MIT License
Classifier: Operating System :: OS Independent
Classifier: Programming Language :: Python :: 3
Requires-Python: >=3.11
